Metadata-Version: 2.1
Name: Missing-Values-101703122
Version: 0.9
Summary: To Handle missing values in a dataset
Home-page: https://github.com/Avani-Agarwal1999/Missing_Values_101703122.git
Author: Avani Agarwal
Author-email: avaniagarwal1999@gmail.com
License: UNKNOWN
Platform: UNKNOWN
Classifier: Programming Language :: Python :: 3
Classifier: License :: OSI Approved :: MIT License
Classifier: Operating System :: OS Independent
Requires-Python: >=3.6
